<?xml version="1.0" encoding="UTF-8"?>
<documenttype key="pptx">
    <type>document</type>
    <titles>
        <title lang="de">OpenXML Präsentation</title>
        <title lang="en">OpenXML Presentation</title>
    </titles>
    <mimetypes>
        <mimetype>application/vnd.openxmlformats-officedocument.presentationml.presentation</mimetype>
    </mimetypes>
    <icons>
        <icon size="16">@PhlexibleMediaTypeBundle/Resources/public/mimetypes16/pptx.gif</icon>
        <icon size="32">@PhlexibleMediaTypeBundle/Resources/public/mimetypes32/pptx.gif</icon>
        <icon size="48">@PhlexibleMediaTypeBundle/Resources/public/mimetypes48/pptx.gif</icon>
        <icon size="256">@PhlexibleMediaTypeBundle/Resources/public/mimetypes256/pptx.gif</icon>
    </icons>
</documenttype>
